ckanext_datapackage_creator-0.0.60-py3.10-nspkg.pth
ckanext/datapackage_creator/__init__.py
ckanext/datapackage_creator/backends.py
ckanext/datapackage_creator/cli.py
ckanext/datapackage_creator/converter.py
ckanext/datapackage_creator/decorators.py
ckanext/datapackage_creator/logic.py
ckanext/datapackage_creator/model.py
ckanext/datapackage_creator/plugin.py
ckanext/datapackage_creator/settings.py
ckanext/datapackage_creator/utils.py
ckanext/datapackage_creator/validation.py
ckanext/datapackage_creator/controllers/__init__.py
ckanext/datapackage_creator/controllers/datapackage_creator.py
ckanext/datapackage_creator/i18n/__init__.py
ckanext/datapackage_creator/public/datapackage_creator/css/styles.css
ckanext/datapackage_creator/public/datapackage_creator/fontawesome/css/all.css
ckanext/datapackage_creator/public/datapackage_creator/fontawesome/css/all.min.css
ckanext/datapackage_creator/public/datapackage_creator/fontawesome/css/brands.css
ckanext/datapackage_creator/public/datapackage_creator/fontawesome/css/brands.min.css
ckanext/datapackage_creator/public/datapackage_creator/fontawesome/css/fontawesome.css
ckanext/datapackage_creator/public/datapackage_creator/fontawesome/css/fontawesome.min.css
ckanext/datapackage_creator/public/datapackage_creator/fontawesome/css/regular.css
ckanext/datapackage_creator/public/datapackage_creator/fontawesome/css/regular.min.css
ckanext/datapackage_creator/public/datapackage_creator/fontawesome/css/solid.css
ckanext/datapackage_creator/public/datapackage_creator/fontawesome/css/solid.min.css
ckanext/datapackage_creator/public/datapackage_creator/fontawesome/css/svg-with-js.css
ckanext/datapackage_creator/public/datapackage_creator/fontawesome/css/svg-with-js.min.css
ckanext/datapackage_creator/public/datapackage_creator/fontawesome/css/v4-font-face.css
ckanext/datapackage_creator/public/datapackage_creator/fontawesome/css/v4-font-face.min.css
ckanext/datapackage_creator/public/datapackage_creator/fontawesome/css/v4-shims.css
ckanext_datapackage_creator-0.0.60.dist-info/LICENSE.md
ckanext_datapackage_creator-0.0.60.dist-info/METADATA
ckanext_datapackage_creator-0.0.60.dist-info/WHEEL
ckanext_datapackage_creator-0.0.60.dist-info/entry_points.txt
ckanext_datapackage_creator-0.0.60.dist-info/namespace_packages.txt
ckanext_datapackage_creator-0.0.60.dist-info/top_level.txt
ckanext_datapackage_creator-0.0.60.dist-info/RECORD
