Metadata-Version: 2.1
Name: ckanext-datapackage-creator
Version: 0.0.60
Summary: Data Package Creator.
Author: Transparência Minas Gerais
License: AGPL
Keywords: CKAN
Classifier: Development Status :: 3 - Alpha
Classifier: License :: OSI Approved :: GNU Affero General Public License v3 or later (AGPLv3+)
Classifier: Programming Language :: Python :: 3.7
Classifier: Programming Language :: Python :: 3.8
Classifier: Programming Language :: Python :: 3.9
License-File: LICENSE.md
Requires-Dist: frictionless (==4.40.8)
Requires-Dist: jsonschema
Requires-Dist: python-slugify
Requires-Dist: frictionless-ckan-mapper
Requires-Dist: openpyxl
Requires-Dist: xlrd
